kagebunshin/__init__.py
kagebunshin/__main__.py
kagebunshin/agent.py
kagebunshin/automation/__init__.py
kagebunshin/automation/behavior.py
kagebunshin/automation/fingerprinting.py
kagebunshin/automation/performance_optimizer.py
kagebunshin/automation/browser/__init__.py
kagebunshin/automation/browser/constants.js
kagebunshin/automation/browser/element-analysis.js
kagebunshin/automation/browser/element-discovery.js
kagebunshin/automation/browser/element-filtering.js
kagebunshin/automation/browser/iframe-processing.js
kagebunshin/automation/browser/main.js
kagebunshin/automation/browser/overlay.js
kagebunshin/automation/browser/text_merger.js
kagebunshin/automation/browser/utils.js
kagebunshin/cli/__init__.py
kagebunshin/cli/runner.py
kagebunshin/communication/__init__.py
kagebunshin/communication/group_chat.py
kagebunshin/config/__init__.py
kagebunshin/config/agent_config.py
kagebunshin/config/settings.py
kagebunshin/config/prompts/blind_agent_system_prompt.md
kagebunshin/config/prompts/diff_summarizer.md
kagebunshin/config/prompts/filesystem_quick_examples.md
kagebunshin/config/prompts/filesystem_usage_guide.md
kagebunshin/config/prompts/kagebunshin_system_prompt_v2.md
kagebunshin/config/prompts/kagebunshin_system_prompt_v3.md
kagebunshin/config/prompts/lame_agent_system_prompt.md
kagebunshin/config/prompts/lame_explainer.md
kagebunshin/config/prompts/prompt_bank.md
kagebunshin/core/__init__.py
kagebunshin/core/agent.py
kagebunshin/core/state.py
kagebunshin/core/state_manager.py
kagebunshin/core/blind_and_lame/__init__.py
kagebunshin/core/blind_and_lame/blind_agent.py
kagebunshin/core/blind_and_lame/lame_agent.py
kagebunshin/tools/__init__.py
kagebunshin/tools/delegation.py
kagebunshin/tools/filesystem.py
kagebunshin/tools/workflow.py
kagebunshin/utils/__init__.py
kagebunshin/utils/formatting.py
kagebunshin/utils/logging.py
kagebunshin/utils/naming.py
kagebunshin-0.1.6.dist-info/METADATA
kagebunshin-0.1.6.dist-info/WHEEL
kagebunshin-0.1.6.dist-info/entry_points.txt
kagebunshin-0.1.6.dist-info/licenses/LICENSE
kagebunshin-0.1.6.dist-info/RECORD
