Metadata-Version: 2.4
Name: kagebunshin
Version: 0.1.6
Summary: AI web automation agent swarm with self-cloning capabilities
Project-URL: Homepage, https://github.com/SiwooBae/kagebunshin
Project-URL: Repository, https://github.com/SiwooBae/kagebunshin
Project-URL: Issues, https://github.com/SiwooBae/kagebunshin/issues
Author-email: Siwoo Bae <cymetric1@gmail.com>
License: MIT
License-File: LICENSE
Keywords: agent,ai,automation,browser,web-scraping
Classifier: Development Status :: 3 - Alpha
Classifier: Intended Audience :: Developers
Classifier: License :: OSI Approved :: MIT License
Classifier: Programming Language :: Python :: 3
Classifier: Programming Language :: Python :: 3.13
Classifier: Topic :: Internet :: WWW/HTTP :: Browsers
Classifier: Topic :: Software Development :: Libraries :: Python Modules
Requires-Python: >=3.13
Requires-Dist: html-to-markdown>=1.9.0
Requires-Dist: html2text>=2025.4.15
Requires-Dist: jinja2>=3.1.6
Requires-Dist: langchain-openai>=0.3.28
Requires-Dist: langchain>=0.3.27
Requires-Dist: langgraph>=0.6.4
Requires-Dist: numpy>=1.26.0
Requires-Dist: pandas>=2.3.1
Requires-Dist: petname>=2.6
Requires-Dist: playwright>=1.54.0
Requires-Dist: pypdf>=5.9.0
Requires-Dist: pytest>=8.4.1
Requires-Dist: python-dotenv>=0.9.9
Requires-Dist: readability-lxml>=0.8.4.1
Requires-Dist: readability>=0.3.2
Requires-Dist: redis>=6.4.0
Requires-Dist: requests>=2.31.0
Requires-Dist: textual>=5.3.0
Requires-Dist: tqdm>=4.66.0
Provides-Extra: dev
Requires-Dist: black>=23.0.0; extra == 'dev'
Requires-Dist: flake8>=6.0.0; extra == 'dev'
Requires-Dist: isort>=5.12.0; extra == 'dev'
Requires-Dist: mypy>=1.5.0; extra == 'dev'
Requires-Dist: pytest-asyncio>=0.21.0; extra == 'dev'
Requires-Dist: pytest>=7.0.0; extra == 'dev'
